manifest/__init__.py
manifest/httpdownloader.py
manifest/main.py
manifest/s3downloader.py
manifest/sftpdownloader.py
manifest/utils.py
manifest_ingest-0.6.0.dist-info/licenses/AUTHORS.md
manifest_ingest-0.6.0.dist-info/licenses/LICENSE
manifest_ingest-0.6.0.dist-info/METADATA
manifest_ingest-0.6.0.dist-info/WHEEL
manifest_ingest-0.6.0.dist-info/entry_points.txt
manifest_ingest-0.6.0.dist-info/top_level.txt
manifest_ingest-0.6.0.dist-info/RECORD
