Metadata-Version: 2.4
Name: manifest-ingest
Version: 0.6.0
Summary: Download a project JSON manifest and its media files via SFTP, HTTP or Amazon S3. This tool was developed for internal use on all X Studios interactive installations which need to have the ability to run 'offline' when there is no active network connection..
Author-email: Tim Santor <tsantor@xstudios.com>
Classifier: Development Status :: 5 - Production/Stable
Classifier: Intended Audience :: Developers
Classifier: Natural Language :: English
Classifier: Programming Language :: Python :: 3.10
Classifier: Programming Language :: Python :: 3.11
Classifier: Programming Language :: Python :: 3.12
Requires-Python: >=3.10
License-File: LICENSE
License-File: AUTHORS.md
Requires-Dist: boto3>=1.38.2
Requires-Dist: paramiko>=2.12.0
Requires-Dist: pysftp>=0.2.9
Requires-Dist: requests>=2.32.3
Requires-Dist: rich>=14.0.0
Requires-Dist: tenacity>=9.1.2
Dynamic: license-file
